LICENSE
MANIFEST.in
README.md
setup.py
bin/tekover
tekover/__init__.py
tekover/tekover.py
tekover.egg-info/PKG-INFO
tekover.egg-info/SOURCES.txt
tekover.egg-info/dependency_links.txt
tekover.egg-info/entry_points.txt
tekover.egg-info/not-zip-safe
tekover.egg-info/requires.txt
tekover.egg-info/top_level.txt
tekover/data/__init__.py
tekover/data/fingerprints.json
tekover/data/resolvers.txt
tekover/data/subdomain-wordlist.txt